falcon_telegraf
