Metadata-Version: 2.1
Name: falcon-telegraf-middleware
Version: 2018.10.12.2
Summary: Falcon to Telegraf middlewares
Home-page: https://github.com/Webinterpret/falcon-telegraf-middleware
Author: Webinterpret
Author-email: funky_chicken@webinterpret.com
License: UNKNOWN
Platform: UNKNOWN
Classifier: Intended Audience :: Developers
Classifier: Natural Language :: English
Classifier: Operating System :: OS Independent
Classifier: Programming Language :: Python
Classifier: Programming Language :: Python :: 3.5
Classifier: Programming Language :: Python :: 3.6
Classifier: Development Status :: 4 - Beta
Classifier: License :: OSI Approved :: MIT License
